dora_rdt_1b/RoboticsDiffusionTransformer/.git
dora_rdt_1b/RoboticsDiffusionTransformer/.gitignore
dora_rdt_1b/RoboticsDiffusionTransformer/LICENSE
dora_rdt_1b/RoboticsDiffusionTransformer/README.md
dora_rdt_1b/RoboticsDiffusionTransformer/assets/head.png
dora_rdt_1b/RoboticsDiffusionTransformer/assets/iclr2025_poster.png
dora_rdt_1b/RoboticsDiffusionTransformer/configs/base.yaml
dora_rdt_1b/RoboticsDiffusionTransformer/configs/calvin_rel_traj_location_bounds_task_ABC_D.json
dora_rdt_1b/RoboticsDiffusionTransformer/configs/dataset_control_freq.json
dora_rdt_1b/RoboticsDiffusionTransformer/configs/dataset_img_keys.json
dora_rdt_1b/RoboticsDiffusionTransformer/configs/dataset_stat.json
dora_rdt_1b/RoboticsDiffusionTransformer/configs/finetune_datasets.json
dora_rdt_1b/RoboticsDiffusionTransformer/configs/finetune_sample_weights.json
dora_rdt_1b/RoboticsDiffusionTransformer/configs/pretrain_datasets.json
dora_rdt_1b/RoboticsDiffusionTransformer/configs/pretrain_sample_weights.json
dora_rdt_1b/RoboticsDiffusionTransformer/configs/state_vec.py
dora_rdt_1b/RoboticsDiffusionTransformer/configs/zero2.json
dora_rdt_1b/RoboticsDiffusionTransformer/data/.gitignore
dora_rdt_1b/RoboticsDiffusionTransformer/data/agilex/hdf5totfrecords.py
dora_rdt_1b/RoboticsDiffusionTransformer/data/aloha/hdf5totfrecords.py
dora_rdt_1b/RoboticsDiffusionTransformer/data/aloha/unzip_data.sh
dora_rdt_1b/RoboticsDiffusionTransformer/data/bridgev2/bridgedata_numpy_to_tfrecord.py
dora_rdt_1b/RoboticsDiffusionTransformer/data/bridgev2/bridgedata_raw_to_numpy.py
dora_rdt_1b/RoboticsDiffusionTransformer/data/bridgev2/download.sh
dora_rdt_1b/RoboticsDiffusionTransformer/data/calvin/download.sh
dora_rdt_1b/RoboticsDiffusionTransformer/data/calvin/hdf5totfrecords.py
dora_rdt_1b/RoboticsDiffusionTransformer/data/compute_dataset_stat.py
dora_rdt_1b/RoboticsDiffusionTransformer/data/compute_dataset_stat_hdf5.py
dora_rdt_1b/RoboticsDiffusionTransformer/data/empty_lang_embed.pt
dora_rdt_1b-0.3.13.dist-info/METADATA
dora_rdt_1b-0.3.13.dist-info/WHEEL
dora_rdt_1b-0.3.13.dist-info/entry_points.txt
dora_rdt_1b-0.3.13.dist-info/RECORD
