Metadata-Version: 2.4
Name: dora-rdt-1b
Version: 0.3.13
Summary: Dora Node for RDT 1B
License: MIT
Author: Haixuan Xavier Tao
Author-email: tao.xavier@outlook.com
Requires-Python: >=3.9
Classifier: License :: OSI Approved :: MIT License
Classifier: Programming Language :: Python :: 3
Classifier: Programming Language :: Python :: 3.9
Classifier: Programming Language :: Python :: 3.10
Classifier: Programming Language :: Python :: 3.11
Classifier: Programming Language :: Python :: 3.12
Classifier: Programming Language :: Python :: 3.13
Classifier: Programming Language :: Python :: 3.14
Requires-Dist: accelerate (>=0.33)
Requires-Dist: diffusers (==0.27.2)
Requires-Dist: dora-rs (>=0.3.9)
Requires-Dist: h5py (==3.11.0)
Requires-Dist: huggingface_hub (==0.23.5)
Requires-Dist: imgaug (==0.4.0)
Requires-Dist: modelscope (>=1.18.1)
Requires-Dist: numpy (>1.24.4)
Requires-Dist: opencv-python (>=4.1.1)
Requires-Dist: packaging (==24.0)
Requires-Dist: qwen-vl-utils (>=0.0.2)
Requires-Dist: sentencepiece (==0.2.0)
Requires-Dist: timm (==1.0.3)
Requires-Dist: torch (>=2.7.0)
Requires-Dist: torchaudio (>=2.7.0)
Requires-Dist: torchvision (>=0.22)
Requires-Dist: transformers (>=4.45)
Requires-Dist: wandb (==0.17.0)
